{
  "required": true,
  "minVersion": "0.8",
  "package": "tfc.dynamicportals.mixin",
  "compatibilityLevel": "JAVA_8",
  "refmap": "dynamicportals.refmap.json",
  "mixins": [
    "core.collision.N",
    "core.collision.N1",
    "core.collision.ShapesMixin",
    "core.data.LevelMixin",
    "core.data.PlayerListMixin",
    "core.data.ServerLevelMixin",
    "core.data.ServerMixin",
    "core.debug.ServerMixin"
  ],
  "client": [
    "client.access.ClientLevelAccessor",
    "client.access.GameRenderAccess",
    "client.access.LevelRenderAccess",
    "client.access.MCAccessor",
    "client.data.ClientLevelMixin",
    "client.data.MinecraftMixin",
    "client.debug.LevelRendererMixin",
    "client.render.LevelRendererMixin",
    "client.render.gl.RenderSystemMixin",
    "client.ClientPortalTypeAttachments"
  ],
  "injectors": {
    "defaultRequire": 1
  }
}
